{"type":"struct","fields":[{"name":"_id","type":"string","nullable":true,"metadata":{}},{"name":"about","type":"string","nullable":true,"metadata":{}},{"name":"address","type":"string","nullable":true,"metadata":{}},{"name":"age","type":"integer","nullable":true,"metadata":{}},{"name":"company","type":"string","nullable":true,"metadata":{}},{"name":"email","type":"string","nullable":true,"metadata":{}},{"name":"eyeColor","type":"string","nullable":true,"metadata":{}},{"name":"favoriteFruit","type":"string","nullable":true,"metadata":{}},{"name":"gender","type":"string","nullable":true,"metadata":{}},{"name":"name","type":"string","nullable":true,"metadata":{}},{"name":"phone","type":"string","nullable":true,"metadata":{}},{"name":"registered","type":"timestamp","nullable":true,"metadata":{}},{"name":"tags","type":{"type":"array","elementType":"string","containsNull":true},"nullable":true,"metadata":{}}]}